indiapost_geocode/__init__.py
indiapost_geocode/digipin.py
indiapost_geocode-1.0.0.dist-info/licenses/LICENSE
indiapost_geocode-1.0.0.dist-info/METADATA
indiapost_geocode-1.0.0.dist-info/WHEEL
indiapost_geocode-1.0.0.dist-info/top_level.txt
indiapost_geocode-1.0.0.dist-info/RECORD
