Metadata-Version: 2.4
Name: indiapost-geocode
Version: 1.0.0
Summary: DIGIPIN encoder/decoder for India Post geocoding
Author-email: Divyansh Pandey <your.email@example.com>
License: MIT
Project-URL: Homepage, https://github.com/divyanshpandey/digipin
Project-URL: Repository, https://github.com/divyanshpandey/digipin
Keywords: digipin,geocoding,india-post,geolocation
Classifier: Programming Language :: Python :: 3
Classifier: License :: OSI Approved :: MIT License
Classifier: Operating System :: OS Independent
Requires-Python: >=3.7
License-File: LICENSE
Dynamic: license-file
